hetzner_fix_report/__init__.py
hetzner_fix_report/hetzner_fix_report.py
hetzner_fix_report-0.11.0.data/scripts/hetzner-fix-report
hetzner_fix_report-0.11.0.dist-info/AUTHORS
hetzner_fix_report-0.11.0.dist-info/LICENSE
hetzner_fix_report-0.11.0.dist-info/METADATA
hetzner_fix_report-0.11.0.dist-info/WHEEL
hetzner_fix_report-0.11.0.dist-info/pbr.json
hetzner_fix_report-0.11.0.dist-info/top_level.txt
hetzner_fix_report-0.11.0.dist-info/RECORD
