Metadata-Version: 2.1
Name: hetzner-fix-report
Version: 0.11.0
Summary: This package demonstrates building and publishing Python Packages with GitHubs infrastructure
Home-page: UNKNOWN
Author: Felix
Author-email: 10831300+flxai@users.noreply.github.com
License: UNKNOWN
Project-URL: Source Code, https://github.com/flxai/hetzner-fix-report
Project-URL: Bug Tracker, https://github.com/flxai/hetzner-fix-report/issues
Project-URL: Documentation, https://hetzner-fix-report.readthedocs.io
Platform: UNKNOWN
Requires-Dist: pbr (==5.4.4)
Requires-Dist: pdftotext (>=2.1.4)
Requires-Dist: numpy (>=1.18.4)
Requires-Dist: pandas (>=1.0.3)
Requires-Dist: regex (>=2020.6.8)
